{"id":202571365,"title":"Gypsy","year":1993,"genres":["Musical & Performing Arts","Comedy"],"mpaa_rating":"Unrated","runtime":142,"release_dates":{"dvd":"2005-03-15"},"ratings":{"critics_rating":"Rotten","critics_score":40,"audience_rating":"Upright","audience_score":76},"synopsis":"","posters":{"thumbnail":"http://resizing.flixster.com/jeZqfK0ndyYyDma-aQu439GxXKc=/54x74/dkpu1ddg7pbsk.cloudfront.net/movie/95/48/954843_ori.jpg","profile":"http://resizing.flixster.com/jeZqfK0ndyYyDma-aQu439GxXKc=/54x74/dkpu1ddg7pbsk.cloudfront.net/movie/95/48/954843_ori.jpg","detailed":"http://resizing.flixster.com/jeZqfK0ndyYyDma-aQu439GxXKc=/54x74/dkpu1ddg7pbsk.cloudfront.net/movie/95/48/954843_ori.jpg","original":"http://resizing.flixster.com/jeZqfK0ndyYyDma-aQu439GxXKc=/54x74/dkpu1ddg7pbsk.cloudfront.net/movie/95/48/954843_ori.jpg"},"abridged_cast":[{"name":"Bette Midler","id":"162659059","characters":["Rose"]},{"name":"Peter Riegert","id":"162662375","characters":["Herbie"]},{"name":"Cynthia Gibb","id":"162690350","characters":["Louise"]},{"name":"Jennifer Rae Beck","id":"770863115","characters":["June"]},{"name":"Edward Asner","id":"162659188","characters":["Pop"]}],"abridged_directors":[{"name":"Emile Ardolino"}],"studio":"Cabin Fever Entertainment","alternate_ids":{"imdb":"0107065"},"links":{"self":"http://api.rottentomatoes.com/api/public/v1.0/movie_alias.json?type=imdb&id=0107065","alternate":"http://www.rottentomatoes.com/m/1045328-gypsy/","cast":"http://api.rottentomatoes.com/api/public/v1.0/movies/202571365/cast.json","reviews":"http://api.rottentomatoes.com/api/public/v1.0/movies/202571365/reviews.json","similar":"http://api.rottentomatoes.com/api/public/v1.0/movies/202571365/similar.json","canonical":"http://api.rottentomatoes.com/api/public/v1.0/movies/202571365.json"},"link_template":"http://api.rottentomatoes.com/api/public/v1.0/movie_alias.json?type=imdb&id={alias-id}"}