{"id":14063,"title":"Homegrown","year":1998,"genres":["Drama","Art House & International","Mystery & Suspense","Comedy"],"mpaa_rating":"R","runtime":102,"release_dates":{"theater":"1998-01-01","dvd":"1998-09-01"},"ratings":{"critics_rating":"Rotten","critics_score":47,"audience_rating":"Spilled","audience_score":50},"synopsis":"","posters":{"thumbnail":"http://resizing.flixster.com/QDWUkGbV6yvk8wvQ12tb-g98U4I=/54x78/dkpu1ddg7pbsk.cloudfront.net/movie/27/28/272817_ori.jpg","profile":"http://resizing.flixster.com/QDWUkGbV6yvk8wvQ12tb-g98U4I=/54x78/dkpu1ddg7pbsk.cloudfront.net/movie/27/28/272817_ori.jpg","detailed":"http://resizing.flixster.com/QDWUkGbV6yvk8wvQ12tb-g98U4I=/54x78/dkpu1ddg7pbsk.cloudfront.net/movie/27/28/272817_ori.jpg","original":"http://resizing.flixster.com/QDWUkGbV6yvk8wvQ12tb-g98U4I=/54x78/dkpu1ddg7pbsk.cloudfront.net/movie/27/28/272817_ori.jpg"},"abridged_cast":[{"name":"Billy Bob Thornton","id":"162652889","characters":["Jack"]},{"name":"Hank Azaria","id":"162695372","characters":["Carter"]},{"name":"Kelly Lynch","id":"162672247","characters":["Lucy"]},{"name":"Ryan Phillippe","id":"162676004","characters":["Harlan"]},{"name":"Judge Reinhold","id":"162668950","characters":["Policeman"]}],"abridged_directors":[{"name":"Stephen Gyllenhaal"}],"studio":"Sony Pictures Home Entertainment","alternate_ids":{"imdb":"0119305"},"links":{"self":"http://api.rottentomatoes.com/api/public/v1.0/movie_alias.json?type=imdb&id=0119305","alternate":"http://www.rottentomatoes.com/m/homegrown/","cast":"http://api.rottentomatoes.com/api/public/v1.0/movies/14063/cast.json","reviews":"http://api.rottentomatoes.com/api/public/v1.0/movies/14063/reviews.json","similar":"http://api.rottentomatoes.com/api/public/v1.0/movies/14063/similar.json","canonical":"http://api.rottentomatoes.com/api/public/v1.0/movies/14063.json"},"link_template":"http://api.rottentomatoes.com/api/public/v1.0/movie_alias.json?type=imdb&id={alias-id}"}