{"id":12456,"title":"Held Up","year":2000,"genres":["Comedy"],"mpaa_rating":"PG-13","runtime":89,"critics_consensus":"","release_dates":{"theater":"2000-05-12","dvd":"2000-08-29"},"ratings":{"critics_rating":"Rotten","critics_score":17,"audience_rating":"Spilled","audience_score":43},"synopsis":"","posters":{"thumbnail":"http://resizing.flixster.com/EdMP1_j6Pd12wYA0P05jxovnPaw=/54x76/dkpu1ddg7pbsk.cloudfront.net/movie/26/54/265495_ori.jpg","profile":"http://resizing.flixster.com/EdMP1_j6Pd12wYA0P05jxovnPaw=/54x76/dkpu1ddg7pbsk.cloudfront.net/movie/26/54/265495_ori.jpg","detailed":"http://resizing.flixster.com/EdMP1_j6Pd12wYA0P05jxovnPaw=/54x76/dkpu1ddg7pbsk.cloudfront.net/movie/26/54/265495_ori.jpg","original":"http://resizing.flixster.com/EdMP1_j6Pd12wYA0P05jxovnPaw=/54x76/dkpu1ddg7pbsk.cloudfront.net/movie/26/54/265495_ori.jpg"},"abridged_cast":[{"name":"Jamie Foxx","id":"162652975","characters":["Michael"]},{"name":"Nia Long","id":"162661398","characters":["Rae"]},{"name":"Barry Corbin","id":"364638771","characters":["Pembry"]},{"name":"John Cullum","id":"770670458","characters":["Jack"]},{"name":"Jake Busey","id":"351527582","characters":["Beaumont"]}],"abridged_directors":[{"name":"Steve Rash"}],"studio":"Trimark","alternate_ids":{"imdb":"0165831"},"links":{"self":"http://api.rottentomatoes.com/api/public/v1.0/movie_alias.json?type=imdb&id=0165831","alternate":"http://www.rottentomatoes.com/m/held_up/","cast":"http://api.rottentomatoes.com/api/public/v1.0/movies/12456/cast.json","reviews":"http://api.rottentomatoes.com/api/public/v1.0/movies/12456/reviews.json","similar":"http://api.rottentomatoes.com/api/public/v1.0/movies/12456/similar.json","canonical":"http://api.rottentomatoes.com/api/public/v1.0/movies/12456.json"},"link_template":"http://api.rottentomatoes.com/api/public/v1.0/movie_alias.json?type=imdb&id={alias-id}"}